<?xml version="1.0" encoding="UTF-8"?>

<schema-set prefer-inline="true" generate-all="false" package="org.dataone.service.types" >
     <class-decorator class="org.jibx.schema.codegen.extend.CollectionMethodsDecorator"/>

<!--    <schema name="common.xsd"  includes="Identifier NodeReference Principal ObjectFormat Checksum ChecksumAlgorithm" />
    <schema name="systemmetadata.xsd" includes="systemMetadata AccessRule ReplicationPolicy SystemMetadata" />

    <schema name="logging.xsd" includes="log LogEntry Event"/>
    <schema name="listobjects.xsd" includes="listObjects ListObjects ObjectInfo" /> -->
    <schema-set names="common.xsd" prefix="common">
        <schema name="common.xsd"  includes="Identifier NodeReference Principal ObjectFormat Checksum ChecksumAlgorithm" />
    </schema-set>
    <schema-set names="systemmetadata.xsd" prefix="d1" namespaces="http://dataone.org/service/types/SystemMetadata/0.1">
        <schema name="systemmetadata.xsd" includes="systemMetadata AccessRule ReplicationPolicy SystemMetadata" />
        <!-- may need to modify schema to support this type of notation
            <namespace uri="http://www.w3.org/2001/XMLSchema-instance" default="none" prefix="xsi"/>
            <value style="attribute" ns="http://www.w3.org/2001/XMLSchema-instance" name="schemaLocation" field="schemaLocation" get-method="getSchemaLocation" set-method="setSchemaLocation"   default="http://dataone.org/service/types/ListObjects/0.1 http://dataone.org/service/types/ListObjects/0.1/listobjects.xsd"  usage="optional"/>
        -->
    </schema-set>
    <schema-set names="logging.xsd" prefix="d1" namespaces="http://dataone.org/service/types/logging/0.1">
        <schema name="logging.xsd" includes="log LogEntry Event"/>
    </schema-set>
    <schema-set names="listobjects.xsd" prefix="d1">
        <schema name="listobjects.xsd" includes="listObjects ListObjects ObjectInfo" />
    </schema-set>
</schema-set>